gym_panda_env/__init__.py
gym_panda_env/envs/__init__.py
gym_panda_env/envs/panda_env.py
gymPanda_env-1.1.2.dist-info/METADATA
gymPanda_env-1.1.2.dist-info/WHEEL
gymPanda_env-1.1.2.dist-info/top_level.txt
gymPanda_env-1.1.2.dist-info/RECORD
