Metadata-Version: 2.1
Name: gymPanda-env
Version: 1.1.2
Summary: A OpenAI Gym Env for Panda arm
Home-page: UNKNOWN
License: UNKNOWN
Platform: UNKNOWN
Requires-Dist: gym
